{"id":"form-based-authentication;using-username-and-password-to-log-in;chrome-headless-shell-127-0-6533-99;linux","name":"Using username and password to log in","title":"Using username and password to log in","manual":false,"testSteps":[{"number":1,"description":"Using username and password to log in #1 - username: tomsmith, password: SuperSecretPassword!, outcome: succeeded","startTime":"2024-08-07T16:48:58.571Z","children":[{"number":2,"description":"Given Alice starts with the \"Form Authentication\" example","startTime":"2024-08-07T16:48:58.575Z","children":[{"number":3,"description":"Alice navigates to \"/\"","startTime":"2024-08-07T16:48:58.599Z","children":[],"reportData":[],"screenshots":[{"screenshot":"photo-linux-chrome-headless-shell-127.0.6533.99-alice-navigates-to-362cc3b221.png","screenshotName":"photo-linux-chrome-headless-shell-127.0.6533.99-alice-navigates-to-362cc3b221.png","timeStamp":1723049338875}],"duration":204,"result":"SUCCESS"},{"number":4,"description":"Alice picks example called Form Authentication","startTime":"2024-08-07T16:48:58.887Z","children":[{"number":5,"description":"Alice clicks on the first of available examples where Text does equal \"Form Authentication\"","startTime":"2024-08-07T16:48:58.888Z","children":[],"reportData":[],"screenshots":[{"screenshot":"photo-linux-chrome-headless-shell-127.0.6533.99-alice-clicks-on-the-fi-42178b1051.png","screenshotName":"photo-linux-chrome-headless-shell-127.0.6533.99-alice-clicks-on-the-fi-42178b1051.png","timeStamp":1723049339605}],"duration":650,"result":"SUCCESS"}],"reportData":[],"screenshots":[],"duration":722,"result":"SUCCESS"}],"reportData":[],"screenshots":[],"duration":1046,"result":"SUCCESS"},{"number":6,"description":"When she logs in using \"tomsmith\" and \"SuperSecretPassword!\"","startTime":"2024-08-07T16:48:59.621Z","children":[{"number":7,"description":"Alice logs in as tomsmith","startTime":"2024-08-07T16:48:59.634Z","children":[{"number":8,"description":"Alice enters \"tomsmith\" into username field","startTime":"2024-08-07T16:48:59.634Z","children":[],"reportData":[],"screenshots":[{"screenshot":"photo-linux-chrome-headless-shell-127.0.6533.99-alice-enters-tomsmith-b6a067ace2.png","screenshotName":"photo-linux-chrome-headless-shell-127.0.6533.99-alice-enters-tomsmith-b6a067ace2.png","timeStamp":1723049339757}],"duration":57,"result":"SUCCESS"},{"number":9,"description":"Alice enters \"SuperSecretPassword!\" into password field","startTime":"2024-08-07T16:48:59.762Z","children":[],"reportData":[],"screenshots":[{"screenshot":"photo-linux-chrome-headless-shell-127.0.6533.99-alice-enters-supersec-c1e56dce47.png","screenshotName":"photo-linux-chrome-headless-shell-127.0.6533.99-alice-enters-supersec-c1e56dce47.png","timeStamp":1723049339873}],"duration":48,"result":"SUCCESS"},{"number":10,"description":"Alice clicks on login button","startTime":"2024-08-07T16:48:59.882Z","children":[],"reportData":[],"screenshots":[{"screenshot":"photo-linux-chrome-headless-shell-127.0.6533.99-alice-clicks-on-login-69ad563cef.png","screenshotName":"photo-linux-chrome-headless-shell-127.0.6533.99-alice-clicks-on-login-69ad563cef.png","timeStamp":1723049340071}],"duration":126,"result":"SUCCESS"}],"reportData":[],"screenshots":[],"duration":445,"result":"SUCCESS"}],"reportData":[],"screenshots":[],"duration":468,"result":"SUCCESS"},{"number":11,"description":"Then she should see that authentication has succeeded","startTime":"2024-08-07T16:49:00.090Z","children":[{"number":12,"description":"Alice verifies that authentication has succeeded","startTime":"2024-08-07T16:49:00.106Z","children":[{"number":13,"description":"Alice verifies that flash alert is present","startTime":"2024-08-07T16:49:00.107Z","children":[{"number":14,"description":"Alice ensures that flash message does become visible","startTime":"2024-08-07T16:49:00.107Z","children":[],"reportData":[],"screenshots":[{"screenshot":"photo-linux-chrome-headless-shell-127.0.6533.99-alice-ensures-that-fla-69ad563cef.png","screenshotName":"photo-linux-chrome-headless-shell-127.0.6533.99-alice-ensures-that-fla-69ad563cef.png","timeStamp":1723049340221}],"duration":62,"result":"SUCCESS"}],"reportData":[],"screenshots":[],"duration":122,"result":"SUCCESS"},{"number":15,"description":"Alice ensures that the text of flash message does include \"You logged into a secure area!\"","startTime":"2024-08-07T16:49:00.240Z","children":[],"reportData":[],"screenshots":[{"screenshot":"photo-linux-chrome-headless-shell-127.0.6533.99-alice-ensures-that-the-69ad563cef.png","screenshotName":"photo-linux-chrome-headless-shell-127.0.6533.99-alice-ensures-that-the-69ad563cef.png","timeStamp":1723049340303}],"duration":17,"result":"SUCCESS"}],"reportData":[],"screenshots":[],"duration":203,"result":"SUCCESS"}],"reportData":[],"screenshots":[],"duration":229,"result":"SUCCESS"}],"reportData":[],"screenshots":[],"duration":1759,"result":"SUCCESS"},{"number":16,"description":"Using username and password to log in #2 - username: foobar, password: barfoo, outcome: failed","startTime":"2024-08-07T16:49:00.335Z","children":[{"number":17,"description":"Given Alice starts with the \"Form Authentication\" example","startTime":"2024-08-07T16:49:00.336Z","children":[{"number":18,"description":"Alice navigates to \"/\"","startTime":"2024-08-07T16:49:00.348Z","children":[],"reportData":[],"screenshots":[{"screenshot":"photo-linux-chrome-headless-shell-127.0.6533.99-alice-navigates-to-362cc3b221.png","screenshotName":"photo-linux-chrome-headless-shell-127.0.6533.99-alice-navigates-to-362cc3b221.png","timeStamp":1723049340456}],"duration":43,"result":"SUCCESS"},{"number":19,"description":"Alice picks example called Form Authentication","startTime":"2024-08-07T16:49:00.462Z","children":[{"number":20,"description":"Alice clicks on the first of available examples where Text does equal \"Form Authentication\"","startTime":"2024-08-07T16:49:00.462Z","children":[],"reportData":[],"screenshots":[{"screenshot":"photo-linux-chrome-headless-shell-127.0.6533.99-alice-clicks-on-the-fi-42178b1051.png","screenshotName":"photo-linux-chrome-headless-shell-127.0.6533.99-alice-clicks-on-the-fi-42178b1051.png","timeStamp":1723049341040}],"duration":509,"result":"SUCCESS"}],"reportData":[],"screenshots":[],"duration":581,"result":"SUCCESS"}],"reportData":[],"screenshots":[],"duration":718,"result":"SUCCESS"},{"number":21,"description":"When she logs in using \"foobar\" and \"barfoo\"","startTime":"2024-08-07T16:49:01.054Z","children":[{"number":22,"description":"Alice logs in as foobar","startTime":"2024-08-07T16:49:01.064Z","children":[{"number":23,"description":"Alice enters \"foobar\" into username field","startTime":"2024-08-07T16:49:01.064Z","children":[],"reportData":[],"screenshots":[{"screenshot":"photo-linux-chrome-headless-shell-127.0.6533.99-alice-enters-foobar-d6eca4b5c5.png","screenshotName":"photo-linux-chrome-headless-shell-127.0.6533.99-alice-enters-foobar-d6eca4b5c5.png","timeStamp":1723049341172}],"duration":40,"result":"SUCCESS"},{"number":24,"description":"Alice enters \"barfoo\" into password field","startTime":"2024-08-07T16:49:01.184Z","children":[],"reportData":[],"screenshots":[{"screenshot":"photo-linux-chrome-headless-shell-127.0.6533.99-alice-enters-barfoo-8cfa6f78d5.png","screenshotName":"photo-linux-chrome-headless-shell-127.0.6533.99-alice-enters-barfoo-8cfa6f78d5.png","timeStamp":1723049341306}],"duration":41,"result":"SUCCESS"},{"number":25,"description":"Alice clicks on login button","startTime":"2024-08-07T16:49:01.316Z","children":[],"reportData":[],"screenshots":[{"screenshot":"photo-linux-chrome-headless-shell-127.0.6533.99-alice-clicks-on-login-67ab1b0a48.png","screenshotName":"photo-linux-chrome-headless-shell-127.0.6533.99-alice-clicks-on-login-67ab1b0a48.png","timeStamp":1723049341489}],"duration":118,"result":"SUCCESS"}],"reportData":[],"screenshots":[],"duration":429,"result":"SUCCESS"}],"reportData":[],"screenshots":[],"duration":450,"result":"SUCCESS"},{"number":26,"description":"Then she should see that authentication has failed","startTime":"2024-08-07T16:49:01.504Z","children":[{"number":27,"description":"Alice verifies that authentication has failed","startTime":"2024-08-07T16:49:01.513Z","children":[{"number":28,"description":"Alice verifies that flash alert is present","startTime":"2024-08-07T16:49:01.514Z","children":[{"number":29,"description":"Alice ensures that flash message does become visible","startTime":"2024-08-07T16:49:01.514Z","children":[],"reportData":[],"screenshots":[{"screenshot":"photo-linux-chrome-headless-shell-127.0.6533.99-alice-ensures-that-fla-67ab1b0a48.png","screenshotName":"photo-linux-chrome-headless-shell-127.0.6533.99-alice-ensures-that-fla-67ab1b0a48.png","timeStamp":1723049341605}],"duration":45,"result":"SUCCESS"}],"reportData":[],"screenshots":[],"duration":95,"result":"SUCCESS"},{"number":30,"description":"Alice ensures that the text of flash message does include \"Your username is invalid!\"","startTime":"2024-08-07T16:49:01.620Z","children":[],"reportData":[],"screenshots":[{"screenshot":"photo-linux-chrome-headless-shell-127.0.6533.99-alice-ensures-that-the-67ab1b0a48.png","screenshotName":"photo-linux-chrome-headless-shell-127.0.6533.99-alice-ensures-that-the-67ab1b0a48.png","timeStamp":1723049341688}],"duration":16,"result":"SUCCESS"}],"reportData":[],"screenshots":[],"duration":183,"result":"SUCCESS"}],"reportData":[],"screenshots":[],"duration":202,"result":"SUCCESS"}],"reportData":[],"screenshots":[],"duration":1383,"result":"SUCCESS"}],"userStory":{"id":"form-based-authentication","storyName":"Form-Based Authentication","displayName":"Form-Based Authentication","path":"authentication/form-based_authentication","type":"feature","narrative":"In order to learn how to use Serenity/JS with Cucumber and WebdriverIO\nAs a Curious Developer\nI'd like to see an example","pathElements":[{"name":"authentication","description":"Authentication"},{"name":"form-based_authentication","description":"Form-based authentication"}]},"dataTable":{"scenarioOutline":"When she logs in using \"<username>\" and \"<password>\"\nThen she should see that authentication has <outcome>","dataSetDescriptors":[{"name":"","description":"","startRow":0,"rowCount":2}],"headers":["username","password","outcome"],"rows":[{"values":["tomsmith","SuperSecretPassword!","succeeded"],"result":"SUCCESS"},{"values":["foobar","barfoo","failed"],"result":"SUCCESS"}],"predefinedRows":true},"startTime":"2024-08-07T16:48:58.571Z","context":"chrome,linux","driver":"chrome-headless-shell","tags":[{"name":"chrome-headless-shell 127.0.6533.99","type":"browser","browserName":"chrome-headless-shell","browserVersion":"127.0.6533.99","displayName":"chrome-headless-shell 127.0.6533.99"},{"name":"linux","type":"platform","platformName":"linux","platformVersion":"","displayName":"linux"},{"name":"Authentication","type":"capability","displayName":"Authentication"},{"name":"Authentication/Form-Based Authentication","type":"feature","displayName":"Form-Based Authentication"}],"testSource":"JS","description":"[\"The Internet\"](https://the-internet.herokuapp.com/) is an example application\nthat captures prominent and ugly functionality found on the web.\nPerfect for writing automated acceptance tests against 😎\nWith **Serenity/JS** you can use [Markdown](https://en.wikipedia.org/wiki/Markdown)\nto better describe each `Feature` and `Scenario`.","featureTag":{"name":"Authentication/Form-Based Authentication","type":"feature","displayName":"Form-Based Authentication"},"duration":3147}