{"id":"form-based-authentication;using-username-and-password-to-log-in;chrome-114-0-5735-198;linux","name":"Using username and password to log in","title":"Using username and password to log in","manual":false,"testSteps":[{"number":1,"description":"Using username and password to log in #1 - username: tomsmith, password: SuperSecretPassword!, outcome: succeeded","startTime":1689118865037,"children":[{"number":2,"description":"Given Alice starts with the \"Form Authentication\" example","startTime":1689118865043,"children":[{"number":3,"description":"Alice navigates to '/'","startTime":1689118865073,"children":[],"reportData":[],"screenshots":[{"screenshot":"photo-linux-chrome-114.0.5735.198-alice-navigates-to-e59145f70e.png","timeStamp":1689118865440}],"duration":261,"result":"SUCCESS"},{"number":4,"description":"Alice picks example called Form Authentication","startTime":1689118865449,"children":[{"number":5,"description":"Alice clicks on the first of available examples where Text does equal 'Form Authentication'","startTime":1689118865449,"children":[],"reportData":[],"screenshots":[{"screenshot":"photo-linux-chrome-114.0.5735.198-alice-clicks-on-the-first-of-availab-21dfbe98a5.png","timeStamp":1689118866415}],"duration":890,"result":"SUCCESS"}],"reportData":[],"screenshots":[],"duration":973,"result":"SUCCESS"}],"reportData":[],"screenshots":[],"duration":1390,"result":"SUCCESS"},{"number":6,"description":"When she logs in using \"tomsmith\" and \"SuperSecretPassword!\"","startTime":1689118866434,"children":[{"number":7,"description":"Alice logs in as tomsmith","startTime":1689118866448,"children":[{"number":8,"description":"Alice enters 'tomsmith' into username field","startTime":1689118866449,"children":[],"reportData":[],"screenshots":[{"screenshot":"photo-linux-chrome-114.0.5735.198-alice-enters-tomsmith-into-usernam-e461d04b22.png","timeStamp":1689118866634}],"duration":77,"result":"SUCCESS"},{"number":9,"description":"Alice enters 'SuperSecretPassword!' into password field","startTime":1689118866642,"children":[],"reportData":[],"screenshots":[{"screenshot":"photo-linux-chrome-114.0.5735.198-alice-enters-supersecretpassword-b78d74c319.png","timeStamp":1689118866800}],"duration":71,"result":"SUCCESS"},{"number":10,"description":"Alice clicks on login button","startTime":1689118866804,"children":[],"reportData":[],"screenshots":[{"screenshot":"photo-linux-chrome-114.0.5735.198-alice-clicks-on-login-button-a7cbdb3d2b.png","timeStamp":1689118867263}],"duration":363,"result":"SUCCESS"}],"reportData":[],"screenshots":[],"duration":822,"result":"SUCCESS"}],"reportData":[],"screenshots":[],"duration":847,"result":"SUCCESS"},{"number":11,"description":"Then she should see that authentication has succeeded","startTime":1689118867282,"children":[{"number":12,"description":"Alice verifies that authentication has succeeded","startTime":1689118867290,"children":[{"number":13,"description":"Alice verifies that flash alert is present","startTime":1689118867291,"children":[{"number":14,"description":"Alice ensures that flash message does become visible","startTime":1689118867291,"children":[],"reportData":[],"screenshots":[{"screenshot":"photo-linux-chrome-114.0.5735.198-alice-ensures-that-flash-message-doe-a7cbdb3d2b.png","timeStamp":1689118867428}],"duration":70,"result":"SUCCESS"}],"reportData":[],"screenshots":[],"duration":142,"result":"SUCCESS"},{"number":15,"description":"Alice ensures that the text of flash message does include 'You logged into a secure area!'","startTime":1689118867444,"children":[],"reportData":[],"screenshots":[{"screenshot":"photo-linux-chrome-114.0.5735.198-alice-ensures-that-the-text-of-flash-a7cbdb3d2b.png","timeStamp":1689118867545}],"duration":20,"result":"SUCCESS"}],"reportData":[],"screenshots":[],"duration":266,"result":"SUCCESS"}],"reportData":[],"screenshots":[],"duration":285,"result":"SUCCESS"}],"reportData":[],"screenshots":[],"duration":2543,"result":"SUCCESS"},{"number":16,"description":"Using username and password to log in #2 - username: foobar, password: barfoo, outcome: failed","startTime":1689118867587,"children":[{"number":17,"description":"Given Alice starts with the \"Form Authentication\" example","startTime":1689118867588,"children":[{"number":18,"description":"Alice navigates to '/'","startTime":1689118867594,"children":[],"reportData":[],"screenshots":[{"screenshot":"photo-linux-chrome-114.0.5735.198-alice-navigates-to-e59145f70e.png","timeStamp":1689118867752}],"duration":58,"result":"SUCCESS"},{"number":19,"description":"Alice picks example called Form Authentication","startTime":1689118867755,"children":[{"number":20,"description":"Alice clicks on the first of available examples where Text does equal 'Form Authentication'","startTime":1689118867755,"children":[],"reportData":[],"screenshots":[{"screenshot":"photo-linux-chrome-114.0.5735.198-alice-clicks-on-the-first-of-availab-21dfbe98a5.png","timeStamp":1689118868582}],"duration":748,"result":"SUCCESS"}],"reportData":[],"screenshots":[],"duration":830,"result":"SUCCESS"}],"reportData":[],"screenshots":[],"duration":1008,"result":"SUCCESS"},{"number":21,"description":"When she logs in using \"foobar\" and \"barfoo\"","startTime":1689118868596,"children":[{"number":22,"description":"Alice logs in as foobar","startTime":1689118868605,"children":[{"number":23,"description":"Alice enters 'foobar' into username field","startTime":1689118868605,"children":[],"reportData":[],"screenshots":[{"screenshot":"photo-linux-chrome-114.0.5735.198-alice-enters-foobar-into-username-01efdf8061.png","timeStamp":1689118868749}],"duration":54,"result":"SUCCESS"},{"number":24,"description":"Alice enters 'barfoo' into password field","startTime":1689118868753,"children":[],"reportData":[],"screenshots":[{"screenshot":"photo-linux-chrome-114.0.5735.198-alice-enters-barfoo-into-password-ab297ce2e3.png","timeStamp":1689118868899}],"duration":56,"result":"SUCCESS"},{"number":25,"description":"Alice clicks on login button","startTime":1689118868901,"children":[],"reportData":[],"screenshots":[{"screenshot":"photo-linux-chrome-114.0.5735.198-alice-clicks-on-login-button-7645a590fc.png","timeStamp":1689118869332}],"duration":345,"result":"SUCCESS"}],"reportData":[],"screenshots":[],"duration":734,"result":"SUCCESS"}],"reportData":[],"screenshots":[],"duration":754,"result":"SUCCESS"},{"number":26,"description":"Then she should see that authentication has failed","startTime":1689118869350,"children":[{"number":27,"description":"Alice verifies that authentication has failed","startTime":1689118869357,"children":[{"number":28,"description":"Alice verifies that flash alert is present","startTime":1689118869357,"children":[{"number":29,"description":"Alice ensures that flash message does become visible","startTime":1689118869357,"children":[],"reportData":[],"screenshots":[{"screenshot":"photo-linux-chrome-114.0.5735.198-alice-ensures-that-flash-message-doe-7645a590fc.png","timeStamp":1689118869490}],"duration":55,"result":"SUCCESS"}],"reportData":[],"screenshots":[],"duration":136,"result":"SUCCESS"},{"number":30,"description":"Alice ensures that the text of flash message does include 'Your username is invalid!'","startTime":1689118869504,"children":[],"reportData":[],"screenshots":[{"screenshot":"photo-linux-chrome-114.0.5735.198-alice-ensures-that-the-text-of-flash-7645a590fc.png","timeStamp":1689118869599}],"duration":25,"result":"SUCCESS"}],"reportData":[],"screenshots":[],"duration":244,"result":"SUCCESS"}],"reportData":[],"screenshots":[],"duration":262,"result":"SUCCESS"}],"reportData":[],"screenshots":[],"duration":2036,"result":"SUCCESS"}],"userStory":{"id":"form-based-authentication","storyName":"Form-Based Authentication","path":"features/authentication/form_authentication.feature","type":"feature","narrative":"In order to learn how to use Serenity/JS with Cucumber and WebdriverIO\nAs a Curious Developer\nI'd like to see an example"},"dataTable":{"scenarioOutline":"When she logs in using \"<username>\" and \"<password>\"\nThen she should see that authentication has <outcome>","dataSetDescriptors":[{"name":"","description":"","startRow":0,"rowCount":2}],"headers":["username","password","outcome"],"rows":[{"values":["tomsmith","SuperSecretPassword!","succeeded"],"result":"SUCCESS"},{"values":["foobar","barfoo","failed"],"result":"SUCCESS"}],"predefinedRows":true},"startTime":1689118865037,"context":"chrome,linux","driver":"chrome","tags":[{"name":"chrome 114.0.5735.198","type":"browser","browserName":"chrome","browserVersion":"114.0.5735.198","displayName":"chrome 114.0.5735.198"},{"name":"linux","type":"platform","platformName":"linux","platformVersion":"","displayName":"linux"},{"name":"Authentication","type":"capability","displayName":"Authentication"},{"name":"Authentication/Form-Based Authentication","type":"feature","displayName":"Form-Based Authentication"}],"testSource":"Cucumber","description":"[\"The Internet\"](https://the-internet.herokuapp.com/) is an example application\nthat captures prominent and ugly functionality found on the web.\nPerfect for writing automated acceptance tests against 😎\n\nNote: With **Serenity/JS** you can use [Markdown](https://en.wikipedia.org/wiki/Markdown)\nto better describe each `Feature` and `Scenario`.","featureTag":{"name":"Authentication/Form-Based Authentication","type":"feature","displayName":"Form-Based Authentication"},"duration":4586}